pysshconfig.py
pysshconfig-0.0.2.dist-info/METADATA
pysshconfig-0.0.2.dist-info/WHEEL
pysshconfig-0.0.2.dist-info/top_level.txt
pysshconfig-0.0.2.dist-info/RECORD
