Metadata-Version: 2.1
Name: pysshconfig
Version: 0.0.2
Summary: Extremely simple, pure-python library to parse ssh_config files.
Home-page: https://github.com/zfrank/pysshconfig
Author: Francesc Zacarias
Author-email: fzacarias3k@gmail.com
License: LGPL
Project-URL: Bug Tracker, https://github.com/zfrank/pysshconfig/issues
Platform: Any
Classifier: Development Status :: 3 - Alpha
Classifier: Intended Audience :: Developers
Classifier: Intended Audience :: System Administrators
Classifier: License :: OSI Approved :: GNU Lesser General Public License v3 (LGPLv3)
Classifier: Operating System :: OS Independent
Classifier: Programming Language :: Python :: 3
Classifier: Topic :: Software Development :: Libraries
Classifier: Topic :: Utilities
